footsies_gym-0.5.0.dist-info/licenses/LICENSE.txt
footsiesgym/__init__.py
footsiesgym/binary_manager.py
footsiesgym/footsies/__init__.py
footsiesgym/footsies/encoder.py
footsiesgym/footsies/feature_indices.json
footsiesgym/footsies/footsies_env.py
footsiesgym/footsies/typing.py
footsiesgym/footsies/utils.py
footsiesgym/footsies/game/__init__.py
footsiesgym/footsies/game/constants.py
footsiesgym/footsies/game/footsies_bot.py
footsiesgym/footsies/game/footsies_game.py
footsiesgym/footsies/game/proto/__init__.py
footsiesgym/footsies/game/proto/csharp_namespace.proto
footsiesgym/footsies/game/proto/footsies_service.proto
footsiesgym/footsies/game/proto/footsies_service_pb2.py
footsiesgym/footsies/game/proto/footsies_service_pb2_grpc.py
footsiesgym/protoc/include/google/protobuf/any.proto
footsiesgym/protoc/include/google/protobuf/api.proto
footsiesgym/protoc/include/google/protobuf/cpp_features.proto
footsiesgym/protoc/include/google/protobuf/descriptor.proto
footsiesgym/protoc/include/google/protobuf/duration.proto
footsiesgym/protoc/include/google/protobuf/empty.proto
footsiesgym/protoc/include/google/protobuf/field_mask.proto
footsiesgym/protoc/include/google/protobuf/java_features.proto
footsiesgym/protoc/include/google/protobuf/source_context.proto
footsiesgym/protoc/include/google/protobuf/struct.proto
footsiesgym/protoc/include/google/protobuf/timestamp.proto
footsiesgym/protoc/include/google/protobuf/type.proto
footsiesgym/protoc/include/google/protobuf/wrappers.proto
footsiesgym/protoc/include/google/protobuf/compiler/plugin.proto
footsies_gym-0.5.0.dist-info/METADATA
footsies_gym-0.5.0.dist-info/WHEEL
footsies_gym-0.5.0.dist-info/top_level.txt
footsies_gym-0.5.0.dist-info/RECORD
