Metadata-Version: 2.4
Name: footsies-gym
Version: 0.5.0
Summary: A reinforcement learning environment for HiFight's Footsies game
Author-email: Chase McDonald <cmcdonald@example.com>
Maintainer-email: Chase McDonald <cmcdonald@example.com>
License-Expression: MIT
Project-URL: Homepage, https://github.com/cmcdonald/FootsiesGym
Project-URL: Repository, https://github.com/cmcdonald/FootsiesGym
Project-URL: Documentation, https://github.com/cmcdonald/FootsiesGym#readme
Project-URL: Bug Tracker, https://github.com/cmcdonald/FootsiesGym/issues
Keywords: reinforcement learning,multi-agent,fighting game,footsies,gymnasium
Classifier: Development Status :: 4 - Beta
Classifier: Intended Audience :: Developers
Classifier: Intended Audience :: Science/Research
Classifier: Operating System :: POSIX :: Linux
Classifier: Programming Language :: Python :: 3
Classifier: Programming Language :: Python :: 3.8
Classifier: Programming Language :: Python :: 3.9
Classifier: Programming Language :: Python :: 3.10
Classifier: Programming Language :: Python :: 3.11
Classifier: Topic :: Scientific/Engineering :: Artificial Intelligence
Classifier: Topic :: Games/Entertainment :: Simulation
Requires-Python: >=3.8
License-File: LICENSE.txt
Requires-Dist: gymnasium
Requires-Dist: numpy>=1.24.0
Requires-Dist: pettingzoo>=1.24.0
Requires-Dist: grpcio>=1.60.0
Requires-Dist: grpcio-tools>=1.60.0
Requires-Dist: absl-py
Requires-Dist: ray[rllib]>=2.46.0
Requires-Dist: natsort
Requires-Dist: pyarrow>=15.0.0
Requires-Dist: portpicker==1.6.0
Provides-Extra: training
Requires-Dist: wandb>=0.15.0; extra == "training"
Provides-Extra: dev
Requires-Dist: pre-commit; extra == "dev"
Requires-Dist: pytest; extra == "dev"
Requires-Dist: black; extra == "dev"
Requires-Dist: isort; extra == "dev"
Requires-Dist: flake8; extra == "dev"
Provides-Extra: all
Requires-Dist: footsies-gym[dev,training]; extra == "all"
Dynamic: license-file
